url2tree/__init__.py
url2tree/url2tree.py
url2tree-0.1.0.dist-info/AUTHORS.rst
url2tree-0.1.0.dist-info/LICENSE
url2tree-0.1.0.dist-info/METADATA
url2tree-0.1.0.dist-info/WHEEL
url2tree-0.1.0.dist-info/top_level.txt
url2tree-0.1.0.dist-info/RECORD
