Metadata-Version: 2.1
Name: url2tree
Version: 0.1.0
Summary: Python package that analysis url visiting log by using tree structure.
Home-page: https://github.com/xodhx4/url2tree
Author: Taeoh Kim
Author-email: kimtaeoh95@gmail.com
License: MIT license
Keywords: url2tree
Platform: UNKNOWN
Classifier: Development Status :: 2 - Pre-Alpha
Classifier: Intended Audience :: Developers
Classifier: License :: OSI Approved :: MIT License
Classifier: Natural Language :: English
Classifier: Programming Language :: Python :: 3
Classifier: Programming Language :: Python :: 3.6
Classifier: Programming Language :: Python :: 3.7
Requires-Python: >=3, !=3.0.*, !=3.1.*, !=3.2.*, !=3.3.*, !=3.4.*, !=3.5.*
